fastapi_lifespan_manager/__init__.py
fastapi_lifespan_manager/lifespan_manager.py
fastapi_lifespan_manager/py.typed
fastapi_lifespan_manager/types.py
fastapi_lifespan_manager-0.1.4.dist-info/LICENSE
fastapi_lifespan_manager-0.1.4.dist-info/METADATA
fastapi_lifespan_manager-0.1.4.dist-info/WHEEL
fastapi_lifespan_manager-0.1.4.dist-info/RECORD
