Metadata-Version: 2.1
Name: fastapi-lifespan-manager
Version: 0.1.4
Summary: FastAPI Lifespan Manager
Home-page: https://github.com/uriyyo/fastapi-lifespan-manager
License: MIT
Author: Yurii Karabas
Author-email: 1998uriyyo@gmail.com
Requires-Python: >=3.8,<4.0
Classifier: License :: OSI Approved :: MIT License
Classifier: Programming Language :: Python :: 3
Classifier: Programming Language :: Python :: 3.8
Classifier: Programming Language :: Python :: 3.9
Classifier: Programming Language :: Python :: 3.10
Classifier: Programming Language :: Python :: 3.11
Classifier: Programming Language :: Python :: 3.12
Requires-Dist: fastapi (>=0.93.0)
Project-URL: Repository, https://github.com/uriyyo/fastapi-lifespan-manager
